{
  "updated": "2026-07-08T00:02:54.186Z",
  "photos": {
    "box6": [
      {
        "src": "images/garage/box6-1.jpg",
        "caption": "Bin #6 — exterior"
      },
      {
        "src": "images/garage/box6-2.jpg",
        "caption": "Tiffany box, nutcrackers & swag"
      }
    ],
    "box5": [
      {
        "src": "images/garage/box5-1.jpg",
        "caption": "Bin #5 — exterior"
      },
      {
        "src": "images/garage/box5-2.jpg",
        "caption": "Duffel, backpack & LSU coolers"
      }
    ],
    "box4": [
      {
        "src": "images/garage/box4-1.jpg",
        "caption": "Bin #4 — exterior"
      },
      {
        "src": "images/garage/box4-2.jpg",
        "caption": "Burlap blind & ACU camo"
      },
      {
        "src": "images/garage/box4-3.jpg",
        "caption": "Gloves, Scent Killer & accessories"
      }
    ],
    "box3": [
      {
        "src": "images/garage/box3-1.jpg",
        "caption": "Bin #3 — exterior"
      },
      {
        "src": "images/garage/box3-2.jpg",
        "caption": "Paddle & rackets"
      },
      {
        "src": "images/garage/box3-3.jpg",
        "caption": "Tarp & work boots"
      }
    ],
    "box2": [
      {
        "src": "images/garage/box2-1.jpg",
        "caption": "Bin #2 — exterior"
      },
      {
        "src": "images/garage/box2-2.jpg",
        "caption": "Trowel, sandpaper & drop cloth"
      }
    ],
    "box_1783462379723": [
      {
        "src": "images/garage/box_1783462379723-1783462569410.jpg",
        "caption": ""
      },
      {
        "src": "images/garage/box_1783462379723-1783462620934.jpg",
        "caption": ""
      },
      {
        "src": "images/garage/box_1783462379723-1783462803241.jpg",
        "caption": ""
      },
      {
        "src": "images/garage/box_1783462379723-1783466630051.jpg",
        "caption": ""
      }
    ],
    "box7": [
      {
        "src": "images/garage/box7-1783462764555.jpg",
        "caption": ""
      },
      {
        "src": "images/garage/box7-1783468044113.jpg",
        "caption": "Storage bin with coiled extension cords"
      },
      {
        "src": "images/garage/box7-1783462773376.jpg",
        "caption": ""
      }
    ]
  }
}
